BoostMut/.DS_Store
BoostMut/BoostMut_class.py
BoostMut/__init__.py
BoostMut/analysis.py
BoostMut/process_BoostMut.py
BoostMut/run_BoostMut.py
BoostMut/utils.py
BoostMut/benchmarks/amber99_range_rmsf_1000ps.csv
BoostMut/benchmarks/amber99_range_rmsf_100ps.csv
BoostMut/benchmarks/amber99_range_rmsf_150ps.csv
BoostMut/benchmarks/amber99_range_rmsf_200ps.csv
BoostMut/benchmarks/amber99_range_rmsf_250ps.csv
BoostMut/benchmarks/amber99_range_rmsf_300ps.csv
BoostMut/benchmarks/amber99_range_rmsf_350ps.csv
BoostMut/benchmarks/amber99_range_rmsf_400ps.csv
BoostMut/benchmarks/amber99_range_rmsf_450ps.csv
BoostMut/benchmarks/amber99_range_rmsf_500ps.csv
BoostMut/benchmarks/amber99_range_rmsf_50ps.csv
BoostMut/benchmarks/amber99_range_rmsf_550ps.csv
BoostMut/benchmarks/amber99_range_rmsf_600ps.csv
BoostMut/benchmarks/amber99_range_rmsf_650ps.csv
BoostMut/benchmarks/amber99_range_rmsf_700ps.csv
BoostMut/benchmarks/amber99_range_rmsf_750ps.csv
BoostMut/benchmarks/amber99_range_rmsf_800ps.csv
BoostMut/benchmarks/amber99_range_rmsf_850ps.csv
BoostMut/benchmarks/amber99_range_rmsf_900ps.csv
BoostMut/benchmarks/amber99_range_rmsf_950ps.csv
BoostMut/benchmarks/charmm27_range_rmsf_1000ps.csv
BoostMut/benchmarks/charmm27_range_rmsf_100ps.csv
BoostMut/benchmarks/charmm27_range_rmsf_150ps.csv
BoostMut/benchmarks/charmm27_range_rmsf_200ps.csv
BoostMut/benchmarks/charmm27_range_rmsf_250ps.csv
BoostMut/benchmarks/charmm27_range_rmsf_300ps.csv
BoostMut/benchmarks/charmm27_range_rmsf_350ps.csv
BoostMut/benchmarks/charmm27_range_rmsf_400ps.csv
BoostMut/benchmarks/charmm27_range_rmsf_450ps.csv
BoostMut/benchmarks/charmm27_range_rmsf_500ps.csv
BoostMut/benchmarks/charmm27_range_rmsf_50ps.csv
BoostMut/benchmarks/charmm27_range_rmsf_550ps.csv
BoostMut/benchmarks/charmm27_range_rmsf_600ps.csv
BoostMut/benchmarks/charmm27_range_rmsf_650ps.csv
BoostMut/benchmarks/charmm27_range_rmsf_700ps.csv
BoostMut/benchmarks/charmm27_range_rmsf_750ps.csv
BoostMut/benchmarks/charmm27_range_rmsf_800ps.csv
boostmut-1.0.3.post2.dist-info/licenses/AUTHORS.md
boostmut-1.0.3.post2.dist-info/licenses/LICENSE
boostmut-1.0.3.post2.dist-info/METADATA
boostmut-1.0.3.post2.dist-info/WHEEL
boostmut-1.0.3.post2.dist-info/entry_points.txt
boostmut-1.0.3.post2.dist-info/top_level.txt
boostmut-1.0.3.post2.dist-info/RECORD
