Metadata-Version: 2.4
Name: BoostMut
Version: 1.0.3.post2
Summary: a python package to analyze short molecular dynamics simulations for the effect of point mutations on stability
Author-email: "Kerlen T. Korbeld" <k.t.korbeld@rug.nl>, "Maximilian J.L.J. Fürst" <m.j.l.j.furst@rug.nl>
Maintainer-email: "Kerlen T. Korbeld" <k.t.korbeld@rug.nl>
License:                     GNU GENERAL PUBLIC LICENSE
Keywords: molecular simulations
Requires-Python: >=3.9
License-File: LICENSE
License-File: AUTHORS.md
Requires-Dist: MDAnalysis>=2.0.0
Requires-Dist: numpy
Requires-Dist: pandas
Requires-Dist: pydssp
Requires-Dist: freesasa
Requires-Dist: xlsxwriter
Provides-Extra: test
Requires-Dist: pytest>=6.0; extra == "test"
Requires-Dist: pytest-xdist>=2.5; extra == "test"
Requires-Dist: pytest-cov>=3.0; extra == "test"
Provides-Extra: doc
Requires-Dist: sphinx; extra == "doc"
Requires-Dist: sphinx_rtd_theme; extra == "doc"
Dynamic: license-file
